spdclient/__init__.py
spdclient/client.py
spdclient-0.0.1.dist-info/METADATA
spdclient-0.0.1.dist-info/WHEEL
spdclient-0.0.1.dist-info/top_level.txt
spdclient-0.0.1.dist-info/RECORD
