Metadata-Version: 2.1
Name: spdclient
Version: 0.0.1
Summary: Python Wrapper for Scrapyd WebService
Author: Kanchan Sapkota
Author-email: Kanchan Sapkota <kanchansapkota27@gmail.com>
License: MIT
Project-URL: Homepage, https://github.com/kanchansapkota27/spdclient
Project-URL: Bug Tracker, https://github.com/kanchansapkota27/spdclient/issues
Keywords: scrapyd scrapy python scrapydapi scrapyd-client api
Classifier: Programming Language :: Python :: 3
Classifier: License :: OSI Approved :: MIT License
Classifier: Operating System :: OS Independent
Requires-Python: >=3.9
Requires-Dist: httpx (>=0.23.0)
Requires-Dist: pytest (>=7.1.3)
Requires-Dist: pytest-html (>=3.1.1)
